applepy/__init__.py
applepy/backend/__init__.py
applepy/backend/app_kit.py
applepy/backend/ui_kit.py
applepy/base/app.py
applepy/base/binding.py
applepy/base/errors.py
applepy/base/mixins.py
applepy/base/scene.py
applepy/base/utils.py
applepy/base/view.py
applepy/base/transform_mixins/__init__.py
applepy/base/transform_mixins/anchors.py
applepy/base/transform_mixins/base.py
applepy/base/transform_mixins/color.py
applepy/base/transform_mixins/control.py
applepy/base/transform_mixins/layout.py
applepy/base/transform_mixins/visibility.py
applepy/base/types/__init__.py
applepy/base/types/alert.py
applepy/base/types/button.py
applepy/base/types/color.py
applepy/base/types/date.py
applepy/base/types/image.py
applepy/base/types/layout.py
applepy/base/types/progress.py
applepy/base/types/types.py
applepy/scenes/__init__.py
applepy/scenes/empty.py
applepy/scenes/simple_screen.py
applepy/scenes/window.py
applepy/views/__init__.py
applepy/views/feedback.py
applepy/views/menu.py
applepy/views/timer.py
applepy/views/controls/__init__.py
applepy/views/controls/button.py
applepy/views/controls/control.py
applepy/views/controls/date.py
applepy/views/controls/progress.py
applepy/views/controls/text.py
applepy/views/layout/__init__.py
applepy/views/layout/stack_view.py
applepy_ui-0.0.5.dist-info/LICENSE
applepy_ui-0.0.5.dist-info/METADATA
applepy_ui-0.0.5.dist-info/WHEEL
applepy_ui-0.0.5.dist-info/top_level.txt
applepy_ui-0.0.5.dist-info/RECORD
