Metadata-Version: 2.1
Name: applepy-ui
Version: 0.0.5
Summary: Applepy is a UI library inspired by Swift UI that leverages AppKit and UIKit (soon) to create native MacOS, iOS and iPadOS user interfaces in the Python programming language with a declarative syntax.
Author-email: Eduardo Henrique <eduardohleite@gmail.com>
License: MIT License
Project-URL: Homepage, https://github.com/eduardohleite/applepy
Keywords: MacOS,iOS,gui
Classifier: License :: OSI Approved :: MIT License
Classifier: Programming Language :: Python
Classifier: Programming Language :: Python :: 3
Requires-Python: >=3.7
License-File: LICENSE
Requires-Dist: rubicon-objc (>=0.4.5)
Requires-Dist: PyDispatcher (>=2.0.7)
